
        <annotation>
            <folder>images</folder>
            <filename>129.jpg</filename>
            <path>static\userdata\jim\20230817_140728-cucumber_5_Maturity\images\129.jpg</path>
            <source>
                <database>Unknown</database>
            </source>
            <size>
                <width>604</width>
                <height>806</height>
                <depth>3</depth>
            </size>
            <segmented>0</segmented>
        <object>
                    <name>bear</name>
                    <pose>Unspecified</pose>
                    <truncated>0</truncated>
                    <difficult>0</difficult>
                    <bndbox>
                        <xmin>411</xmin>
                        <ymin>62</ymin>
                        <xmax>562</xmax>
                        <ymax>183</ymax>
                    </bndbox>
                </object>
                <object>
                    <name>bear</name>
                    <pose>Unspecified</pose>
                    <truncated>0</truncated>
                    <difficult>0</difficult>
                    <bndbox>
                        <xmin>211</xmin>
                        <ymin>240</ymin>
                        <xmax>344</xmax>
                        <ymax>536</ymax>
                    </bndbox>
                </object>
                </annotation>