
                                      <annotation>
                                          <folder>images</folder>
                                          <filename>264.jpg</filename>
                                          <path>static/userdata/jim/20230825_080328-cucumber_5_Maturity/images/264.jpg</path>
                                          <source>
                                              <database>Unknown</database>
                                          </source>
                                          <size>
                                              <width>604</width>
                                              <height>806</height>
                                              <depth>3</depth>
                                          </size>
                                          <segmented>0</segmented>
                                      <object>
                                                    <name>growth</name>
                                                    <pose>Unspecified</pose>
                                                    <truncated>0</truncated>
                                                    <difficult>0</difficult>
                                                    <bndbox>
                                                        <xmin>264</xmin>
                                                        <ymin>191</ymin>
                                                        <xmax>409</xmax>
                                                        <ymax>599</ymax>
                                                    </bndbox>
                                                </object>
                                                <object>
                                                    <name>bear</name>
                                                    <pose>Unspecified</pose>
                                                    <truncated>0</truncated>
                                                    <difficult>0</difficult>
                                                    <bndbox>
                                                        <xmin>190</xmin>
                                                        <ymin>584</ymin>
                                                        <xmax>281</xmax>
                                                        <ymax>804</ymax>
                                                    </bndbox>
                                                </object>
                                                </annotation>