
        <annotation>
            <folder>images</folder>
            <filename>187.jpg</filename>
            <path>static\userdata\jim\20230821_151642-cucumber_5_Maturity\images\187.jpg</path>
            <source>
                <database>Unknown</database>
            </source>
            <size>
                <width>724</width>
                <height>967</height>
                <depth>3</depth>
            </size>
            <segmented>0</segmented>
        <object>
                    <name>mature</name>
                    <pose>Unspecified</pose>
                    <truncated>0</truncated>
                    <difficult>0</difficult>
                    <bndbox>
                        <xmin>294</xmin>
                        <ymin>581</ymin>
                        <xmax>414</xmax>
                        <ymax>923</ymax>
                    </bndbox>
                </object>
                <object>
                    <name>mature</name>
                    <pose>Unspecified</pose>
                    <truncated>0</truncated>
                    <difficult>0</difficult>
                    <bndbox>
                        <xmin>194</xmin>
                        <ymin>251</ymin>
                        <xmax>341</xmax>
                        <ymax>641</ymax>
                    </bndbox>
                </object>
                <object>
                    <name>mature</name>
                    <pose>Unspecified</pose>
                    <truncated>0</truncated>
                    <difficult>0</difficult>
                    <bndbox>
                        <xmin>439</xmin>
                        <ymin>13</ymin>
                        <xmax>524</xmax>
                        <ymax>407</ymax>
                    </bndbox>
                </object>
                </annotation>