
        <annotation>
            <folder>images</folder>
            <filename>452.jpg</filename>
            <path>static\userdata\jim\20230824_112538-cucumber_5_Maturity\images\452.jpg</path>
            <source>
                <database>Unknown</database>
            </source>
            <size>
                <width>845</width>
                <height>1128</height>
                <depth>3</depth>
            </size>
            <segmented>0</segmented>
        <object>
                    <name>flowering</name>
                    <pose>Unspecified</pose>
                    <truncated>0</truncated>
                    <difficult>0</difficult>
                    <bndbox>
                        <xmin>219</xmin>
                        <ymin>404</ymin>
                        <xmax>730</xmax>
                        <ymax>871</ymax>
                    </bndbox>
                </object>
                </annotation>