
                                      <annotation>
                                          <folder>images</folder>
                                          <filename>491.jpg</filename>
                                          <path>static/userdata/jim/20230824_112538-cucumber_5_Maturity/images/491.jpg</path>
                                          <source>
                                              <database>Unknown</database>
                                          </source>
                                          <size>
                                              <width>845</width>
                                              <height>1128</height>
                                              <depth>3</depth>
                                          </size>
                                          <segmented>0</segmented>
                                      <object>
                                                    <name>mature</name>
                                                    <pose>Unspecified</pose>
                                                    <truncated>0</truncated>
                                                    <difficult>0</difficult>
                                                    <bndbox>
                                                        <xmin>550</xmin>
                                                        <ymin>254</ymin>
                                                        <xmax>678</xmax>
                                                        <ymax>685</ymax>
                                                    </bndbox>
                                                </object>
                                                <object>
                                                    <name>mature</name>
                                                    <pose>Unspecified</pose>
                                                    <truncated>0</truncated>
                                                    <difficult>0</difficult>
                                                    <bndbox>
                                                        <xmin>287</xmin>
                                                        <ymin>122</ymin>
                                                        <xmax>556</xmax>
                                                        <ymax>847</ymax>
                                                    </bndbox>
                                                </object>
                                                </annotation>